elastic/__init__.py
elastic/elastic_notebook.py
elastic/algorithm/__init__.py
elastic/algorithm/baseline.py
elastic/algorithm/optimizer_exact.py
elastic/algorithm/selector.py
elastic/core/__init__.py
elastic/core/common/__init__.py
elastic/core/common/checkpoint_file.py
elastic/core/common/profile_graph_size.py
elastic/core/common/profile_migration_speed.py
elastic/core/common/profile_variable_size.py
elastic/core/graph/__init__.py
elastic/core/graph/cell_execution.py
elastic/core/graph/graph.py
elastic/core/graph/variable_snapshot.py
elastic/core/io/__init__.py
elastic/core/io/adapter.py
elastic/core/io/filesystem_adapter.py
elastic/core/io/migrate.py
elastic/core/io/pickle.py
elastic/core/io/recover.py
elastic/core/mutation/__init__.py
elastic/core/mutation/fingerprint.py
elastic/core/mutation/id_graph.py
elastic/core/mutation/object_hash.py
elastic/core/notebook/__init__.py
elastic/core/notebook/checkpoint.py
elastic/core/notebook/find_input_vars.py
elastic/core/notebook/find_output_vars.py
elastic/core/notebook/restore_notebook.py
elastic/core/notebook/update_graph.py
elastic_notebook_slim-0.0.13.dist-info/licenses/LICENSE
elastic_notebook_slim-0.0.13.dist-info/METADATA
elastic_notebook_slim-0.0.13.dist-info/WHEEL
elastic_notebook_slim-0.0.13.dist-info/top_level.txt
elastic_notebook_slim-0.0.13.dist-info/RECORD
