Metadata-Version: 2.4
Name: elastic-notebook-slim
Version: 0.0.13
Summary: ElasticNotebookのライブラリ版
Home-page: https://github.com/MRyutaro/elastic_notebook_slim
Author-email: m2002r1028@icloud.com
Classifier: Programming Language :: Python :: 3
Classifier: License :: OSI Approved :: MIT License
Classifier: Operating System :: OS Independent
Requires-Python: >=3.6
License-File: LICENSE
Requires-Dist: dill
Requires-Dist: ipykernel
Requires-Dist: ipython
Requires-Dist: lightgbm
Requires-Dist: matplotlib
Requires-Dist: networkx
Requires-Dist: numpy
Requires-Dist: pandas
Requires-Dist: Pympler
Requires-Dist: scipy
Requires-Dist: seaborn
Requires-Dist: torch
Requires-Dist: xxhash
Provides-Extra: dev
Requires-Dist: black; extra == "dev"
Requires-Dist: flake8; extra == "dev"
Requires-Dist: isort; extra == "dev"
Requires-Dist: mypy; extra == "dev"
Requires-Dist: bump2version; extra == "dev"
Dynamic: license-file
